{"page":244,"lines":[{"n":1,"type":"ayah","centered":0,"segments":[{"surah":12,"ayah":70,"text":"ﱁ ﱂ ﱃ ﱄ ﱅ ﱆ ﱇ ﱈ"}]},{"n":2,"type":"ayah","centered":0,"segments":[{"surah":12,"ayah":70,"text":"ﱉ ﱊ ﱋ ﱌ ﱍ ﱎ ﱏ ﱐ"},{"surah":12,"ayah":71,"text":" ﱑ"}]},{"n":3,"type":"ayah","centered":0,"segments":[{"surah":12,"ayah":71,"text":"ﱒ ﱓ ﱔ ﱕ ﱖ"},{"surah":12,"ayah":72,"text":" ﱗ ﱘ ﱙ ﱚ"}]},{"n":4,"type":"ayah","centered":0,"segments":[{"surah":12,"ayah":72,"text":"ﱛ ﱜ ﱝ ﱞ ﱟ ﱠ ﱡ ﱢ ﱣ"},{"surah":12,"ayah":73,"text":" ﱤ ﱥ"}]},{"n":5,"type":"ayah","centered":0,"segments":[{"surah":12,"ayah":73,"text":"ﱦ ﱧ ﱨ ﱩ ﱪ ﱫ ﱬ ﱭ ﱮ ﱯ ﱰ"}]},{"n":6,"type":"ayah","centered":0,"segments":[{"surah":12,"ayah":74,"text":"ﱱ ﱲ ﱳ ﱴ ﱵ ﱶ ﱷ"},{"surah":12,"ayah":75,"text":" ﱸ ﱹ"}]},{"n":7,"type":"ayah","centered":0,"segments":[{"surah":12,"ayah":75,"text":"ﱺ ﱻ ﱼ ﱽ ﱾ ﱿﲀ ﲁ ﲂ ﲃ ﲄ"}]},{"n":8,"type":"ayah","centered":0,"segments":[{"surah":12,"ayah":76,"text":"ﲅ ﲆ ﲇ ﲈ ﲉ ﲊ ﲋ ﲌ"}]},{"n":9,"type":"ayah","centered":0,"segments":[{"surah":12,"ayah":76,"text":"ﲍ ﲎﲏ ﲐ ﲑ ﲒﲓ ﲔ ﲕ ﲖ ﲗ"}]},{"n":10,"type":"ayah","centered":0,"segments":[{"surah":12,"ayah":76,"text":"ﲘ ﲙ ﲚ ﲛ ﲜ ﲝ ﲞﲟ ﲠ ﲡ ﲢ ﲣﲤ"}]},{"n":11,"type":"ayah","centered":0,"segments":[{"surah":12,"ayah":76,"text":"ﲥ ﲦ ﲧ ﲨ ﲩ ﲪ"},{"surah":12,"ayah":77,"text":" ﲫﲬ ﲭ ﲮ"}]},{"n":12,"type":"ayah","centered":0,"segments":[{"surah":12,"ayah":77,"text":"ﲯ ﲰ ﲱ ﲲ ﲳ ﲴﲵ ﲶ ﲷ ﲸ ﲹ"}]},{"n":13,"type":"ayah","centered":0,"segments":[{"surah":12,"ayah":77,"text":"ﲺ ﲻ ﲼﲽ ﲾ ﲿ ﳀ ﳁﳂ ﳃ ﳄ ﳅ"}]},{"n":14,"type":"ayah","centered":0,"segments":[{"surah":12,"ayah":77,"text":"ﳆ ﳇ"},{"surah":12,"ayah":78,"text":" ﳈ ﳉ ﳊ ﳋ ﳌ ﳍ ﳎ ﳏ"}]},{"n":15,"type":"ayah","centered":0,"segments":[{"surah":12,"ayah":78,"text":"ﳐ ﳑ ﳒﳓ ﳔ ﳕ ﳖ ﳗ ﳘ"}]}]}