{"page":258,"lines":[{"n":1,"type":"ayah","centered":0,"segments":[{"surah":14,"ayah":19,"text":"ﱁ ﱂ ﱃ ﱄ ﱅ ﱆ ﱇ ﱈﱉ ﱊ ﱋ"}]},{"n":2,"type":"ayah","centered":0,"segments":[{"surah":14,"ayah":19,"text":"ﱌ ﱍ ﱎ ﱏ ﱐ"},{"surah":14,"ayah":20,"text":" ﱑ ﱒ ﱓ ﱔ ﱕ ﱖ"}]},{"n":3,"type":"ayah","centered":0,"segments":[{"surah":14,"ayah":21,"text":"ﱗ ﱘ ﱙ ﱚ ﱛ ﱜ ﱝ"}]},{"n":4,"type":"ayah","centered":0,"segments":[{"surah":14,"ayah":21,"text":"ﱞ ﱟ ﱠ ﱡ ﱢ ﱣ ﱤ ﱥ ﱦ ﱧ ﱨ"}]},{"n":5,"type":"ayah","centered":0,"segments":[{"surah":14,"ayah":21,"text":"ﱩ ﱪﱫ ﱬ ﱭ ﱮ ﱯ ﱰﱱ ﱲ ﱳ"}]},{"n":6,"type":"ayah","centered":0,"segments":[{"surah":14,"ayah":21,"text":"ﱴ ﱵ ﱶ ﱷ ﱸ ﱹ ﱺ ﱻ"},{"surah":14,"ayah":22,"text":" ﱼ ﱽ ﱾ"}]},{"n":7,"type":"ayah","centered":0,"segments":[{"surah":14,"ayah":22,"text":"ﱿ ﲀ ﲁ ﲂ ﲃ ﲄ ﲅ ﲆ"}]},{"n":8,"type":"ayah","centered":0,"segments":[{"surah":14,"ayah":22,"text":"ﲇﲈ ﲉ ﲊ ﲋ ﲌ ﲍ ﲎ ﲏ"}]},{"n":9,"type":"ayah","centered":0,"segments":[{"surah":14,"ayah":22,"text":"ﲐ ﲑ ﲒ ﲓﲔ ﲕ ﲖ ﲗ ﲘﲙ"}]},{"n":10,"type":"ayah","centered":0,"segments":[{"surah":14,"ayah":22,"text":"ﲚ ﲛ ﲜ ﲝ ﲞ ﲟ ﲠ ﲡ"}]},{"n":11,"type":"ayah","centered":0,"segments":[{"surah":14,"ayah":22,"text":"ﲢ ﲣ ﲤ ﲥﲦ ﲧ ﲨ ﲩ ﲪ"}]},{"n":12,"type":"ayah","centered":0,"segments":[{"surah":14,"ayah":22,"text":"ﲫ ﲬ"},{"surah":14,"ayah":23,"text":" ﲭ ﲮ ﲯ ﲰ ﲱ ﲲ"}]},{"n":13,"type":"ayah","centered":0,"segments":[{"surah":14,"ayah":23,"text":"ﲳ ﲴ ﲵ ﲶ ﲷ ﲸ ﲹ ﲺﲻ ﲼ"}]},{"n":14,"type":"ayah","centered":0,"segments":[{"surah":14,"ayah":23,"text":"ﲽ ﲾ ﲿ"},{"surah":14,"ayah":24,"text":" ﳀ ﳁ ﳂ ﳃ ﳄ ﳅ ﳆ ﳇ"}]},{"n":15,"type":"ayah","centered":0,"segments":[{"surah":14,"ayah":24,"text":"ﳈ ﳉ ﳊ ﳋ ﳌ ﳍ ﳎ ﳏ"}]}]}