{"page":503,"lines":[{"n":1,"type":"ayah","centered":0,"segments":[{"surah":46,"ayah":6,"text":"ﱁ ﱂ ﱃ ﱄ ﱅ ﱆ ﱇ ﱈ ﱉ ﱊ"},{"surah":46,"ayah":7,"text":" ﱋ"}]},{"n":2,"type":"ayah","centered":0,"segments":[{"surah":46,"ayah":7,"text":"ﱌ ﱍ ﱎ ﱏ ﱐ ﱑ ﱒ ﱓ ﱔ ﱕ ﱖ"}]},{"n":3,"type":"ayah","centered":0,"segments":[{"surah":46,"ayah":7,"text":"ﱗ ﱘ ﱙ"},{"surah":46,"ayah":8,"text":" ﱚ ﱛ ﱜﱝ ﱞ ﱟ ﱠ ﱡ ﱢ"}]},{"n":4,"type":"ayah","centered":0,"segments":[{"surah":46,"ayah":8,"text":"ﱣ ﱤ ﱥ ﱦﱧ ﱨ ﱩ ﱪ ﱫ ﱬﱭ ﱮ ﱯ ﱰ ﱱ"}]},{"n":5,"type":"ayah","centered":0,"segments":[{"surah":46,"ayah":8,"text":"ﱲﱳ ﱴ ﱵ ﱶ ﱷ"},{"surah":46,"ayah":9,"text":" ﱸ ﱹ ﱺ ﱻ ﱼ ﱽ"}]},{"n":6,"type":"ayah","centered":0,"segments":[{"surah":46,"ayah":9,"text":"ﱾ ﱿ ﲀ ﲁ ﲂ ﲃ ﲄﲅ ﲆ ﲇ ﲈ ﲉ ﲊ ﲋ ﲌ ﲍ"}]},{"n":7,"type":"ayah","centered":0,"segments":[{"surah":46,"ayah":9,"text":"ﲎ ﲏ ﲐ ﲑ"},{"surah":46,"ayah":10,"text":" ﲒ ﲓ ﲔ ﲕ ﲖ ﲗ ﲘ ﲙ ﲚ"}]},{"n":8,"type":"ayah","centered":0,"segments":[{"surah":46,"ayah":10,"text":"ﲛ ﲜ ﲝ ﲞ ﲟ ﲠ ﲡ ﲢ ﲣﲤ"}]},{"n":9,"type":"ayah","centered":0,"segments":[{"surah":46,"ayah":10,"text":"ﲥ ﲦ ﲧ ﲨ ﲩ ﲪ ﲫ"},{"surah":46,"ayah":11,"text":" ﲬ ﲭ ﲮ"}]},{"n":10,"type":"ayah","centered":0,"segments":[{"surah":46,"ayah":11,"text":"ﲯ ﲰ ﲱ ﲲ ﲳ ﲴ ﲵ ﲶﲷ ﲸ ﲹ ﲺ ﲻ"}]},{"n":11,"type":"ayah","centered":0,"segments":[{"surah":46,"ayah":11,"text":"ﲼ ﲽ ﲾ ﲿ ﳀ"},{"surah":46,"ayah":12,"text":" ﳁ ﳂ ﳃ ﳄ"}]},{"n":12,"type":"ayah","centered":0,"segments":[{"surah":46,"ayah":12,"text":"ﳅ ﳆﳇ ﳈ ﳉ ﳊ ﳋ ﳌ ﳍ"}]},{"n":13,"type":"ayah","centered":0,"segments":[{"surah":46,"ayah":12,"text":"ﳎ ﳏ ﳐ ﳑ ﳒ"},{"surah":46,"ayah":13,"text":" ﳓ ﳔ ﳕ ﳖ"}]},{"n":14,"type":"ayah","centered":0,"segments":[{"surah":46,"ayah":13,"text":"ﳗ ﳘ ﳙ ﳚ ﳛ ﳜ ﳝ ﳞ ﳟ ﳠ"}]},{"n":15,"type":"ayah","centered":0,"segments":[{"surah":46,"ayah":14,"text":"ﳡ ﳢ ﳣ ﳤ ﳥ ﳦ ﳧ ﳨ ﳩ ﳪ"}]}]}