{"page":514,"lines":[{"n":1,"type":"ayah","centered":0,"segments":[{"surah":48,"ayah":24,"text":"ﱁ ﱂ ﱃ ﱄ ﱅ ﱆ ﱇ ﱈ ﱉ ﱊ"}]},{"n":2,"type":"ayah","centered":0,"segments":[{"surah":48,"ayah":24,"text":"ﱋ ﱌ ﱍ ﱎﱏ ﱐ ﱑ ﱒ ﱓ ﱔ ﱕ"}]},{"n":3,"type":"ayah","centered":0,"segments":[{"surah":48,"ayah":25,"text":"ﱖ ﱗ ﱘ ﱙ ﱚ ﱛ ﱜ"}]},{"n":4,"type":"ayah","centered":0,"segments":[{"surah":48,"ayah":25,"text":"ﱝ ﱞ ﱟ ﱠ ﱡﱢ ﱣ ﱤ ﱥ ﱦ"}]},{"n":5,"type":"ayah","centered":0,"segments":[{"surah":48,"ayah":25,"text":"ﱧ ﱨ ﱩ ﱪ ﱫ ﱬ ﱭ ﱮ"}]},{"n":6,"type":"ayah","centered":0,"segments":[{"surah":48,"ayah":25,"text":"ﱯ ﱰﱱ ﱲ ﱳ ﱴ ﱵ ﱶ ﱷﱸ ﱹ ﱺ ﱻ"}]},{"n":7,"type":"ayah","centered":0,"segments":[{"surah":48,"ayah":25,"text":"ﱼ ﱽ ﱾ ﱿ ﲀ ﲁ"},{"surah":48,"ayah":26,"text":" ﲂ ﲃ ﲄ ﲅ"}]},{"n":8,"type":"ayah","centered":0,"segments":[{"surah":48,"ayah":26,"text":"ﲆ ﲇ ﲈ ﲉ ﲊ ﲋ ﲌ ﲍ"}]},{"n":9,"type":"ayah","centered":0,"segments":[{"surah":48,"ayah":26,"text":"ﲎ ﲏ ﲐ ﲑ ﲒ ﲓ ﲔ"}]},{"n":10,"type":"ayah","centered":0,"segments":[{"surah":48,"ayah":26,"text":"ﲕ ﲖ ﲗ ﲘﲙ ﲚ ﲛ ﲜ ﲝ ﲞ ﲟ"}]},{"n":11,"type":"ayah","centered":0,"segments":[{"surah":48,"ayah":27,"text":"ﲠ ﲡ ﲢ ﲣ ﲤ ﲥﲦ ﲧ ﲨ"}]},{"n":12,"type":"ayah","centered":0,"segments":[{"surah":48,"ayah":27,"text":"ﲩ ﲪ ﲫ ﲬ ﲭ ﲮ ﲯ ﲰ"}]},{"n":13,"type":"ayah","centered":0,"segments":[{"surah":48,"ayah":27,"text":"ﲱ ﲲﲳ ﲴ ﲵ ﲶ ﲷ ﲸ ﲹ ﲺ ﲻ"}]},{"n":14,"type":"ayah","centered":0,"segments":[{"surah":48,"ayah":27,"text":"ﲼ ﲽ ﲾ"},{"surah":48,"ayah":28,"text":" ﲿ ﳀ ﳁ ﳂ ﳃ ﳄ"}]},{"n":15,"type":"ayah","centered":0,"segments":[{"surah":48,"ayah":28,"text":"ﳅ ﳆ ﳇ ﳈ ﳉﳊ ﳋ ﳌ ﳍ ﳎ"}]}]}